pineflow/_bundle/__init__.py
pineflow-0.7.4.dist-info/METADATA
pineflow-0.7.4.dist-info/WHEEL
pineflow-0.7.4.dist-info/licenses/LICENSE
pineflow-0.7.4.dist-info/RECORD
